[
  {
    "name": "app/lib/admin/metrics/dimension",
    "type": "package",
    "children": [
      {
        "name": "Admin",
        "type": "class",
        "children": [
          {
            "name": "Metrics",
            "type": "class",
            "children": [
              {
                "name": "Dimension",
                "type": "class",
                "children": [
                  {
                    "name": "BaseDimension",
                    "type": "class",
                    "children": [
                      {
                        "name": "data",
                        "type": "function",
                        "static": false,
                        "location": "app/lib/admin/metrics/dimension/base_dimension.rb:30"
                      },
                      {
                        "name": "load",
                        "type": "function",
                        "static": false,
                        "location": "app/lib/admin/metrics/dimension/base_dimension.rb:44"
                      },
                      {
                        "name": "cache_key",
                        "type": "function",
                        "static": false,
                        "location": "app/lib/admin/metrics/dimension/base_dimension.rb:26"
                      },
                      {
                        "name": "canonicalized_params",
                        "type": "function",
                        "static": false,
                        "location": "app/lib/admin/metrics/dimension/base_dimension.rb:65"
                      }
                    ]
                  },
                  {
                    "name": "TagLanguagesDimension",
                    "type": "class",
                    "children": [
                      {
                        "name": "key",
                        "type": "function",
                        "static": false,
                        "location": "app/lib/admin/metrics/dimension/tag_languages_dimension.rb:11"
                      },
                      {
                        "name": "params",
                        "type": "function",
                        "static": false,
                        "location": "app/lib/admin/metrics/dimension/tag_languages_dimension.rb:50"
                      },
                      {
                        "name": "perform_query",
                        "type": "function",
                        "static": false,
                        "location": "app/lib/admin/metrics/dimension/tag_languages_dimension.rb:17"
                      },
                      {
                        "name": "sql_array",
                        "type": "function",
                        "static": false,
                        "location": "app/lib/admin/metrics/dimension/tag_languages_dimension.rb:21"
                      },
                      {
                        "name": "sql_query_string",
                        "type": "function",
                        "static": false,
                        "location": "app/lib/admin/metrics/dimension/tag_languages_dimension.rb:25"
                      },
                      {
                        "name": "tag_id",
                        "type": "function",
                        "static": false,
                        "location": "app/lib/admin/metrics/dimension/tag_languages_dimension.rb:38"
                      },
                      {
                        "name": "earliest_status_id",
                        "type": "function",
                        "static": false,
                        "location": "app/lib/admin/metrics/dimension/tag_languages_dimension.rb:42"
                      },
                      {
                        "name": "latest_status_id",
                        "type": "function",
                        "static": false,
                        "location": "app/lib/admin/metrics/dimension/tag_languages_dimension.rb:46"
                      }
                    ]
                  },
                  {
                    "name": "QueryHelper",
                    "type": "class",
                    "children": [
                      {
                        "name": "dimension_data_rows",
                        "type": "function",
                        "static": false,
                        "location": "app/lib/admin/metrics/dimension/query_helper.rb:6"
                      },
                      {
                        "name": "sanitized_sql_string",
                        "type": "function",
                        "static": false,
                        "location": "app/lib/admin/metrics/dimension/query_helper.rb:10"
                      }
                    ]
                  }
                ]
              }
            ]
          }
        ]
      }
    ]
  },
  {
    "name": "logger",
    "type": "package",
    "children": [
      {
        "name": "Logger",
        "type": "class",
        "children": [
          {
            "name": "LogDevice",
            "type": "class",
            "children": [
              {
                "name": "write",
                "type": "function",
                "labels": [
                  "log"
                ],
                "static": false,
                "location": "/usr/local/lib/ruby/3.2.0/logger/log_device.rb:31"
              }
            ]
          }
        ]
      }
    ]
  },
  {
    "name": "lib/mastodon",
    "type": "package",
    "children": [
      {
        "name": "Mastodon",
        "type": "class",
        "children": [
          {
            "name": "Snowflake",
            "type": "class",
            "children": [
              {
                "name": "id_at",
                "type": "function",
                "static": true,
                "location": "lib/mastodon/snowflake.rb:99"
              }
            ]
          }
        ]
      }
    ]
  },
  {
    "name": "ruby",
    "type": "package",
    "children": [
      {
        "name": "Marshal",
        "type": "class",
        "children": [
          {
            "name": "dump",
            "type": "function",
            "labels": [
              "serialize"
            ],
            "static": true,
            "location": "Marshal.dump"
          }
        ]
      }
    ]
  },
  {
    "type": "database",
    "name": "Database",
    "children": [
      {
        "type": "query",
        "name": "SELECT COALESCE(statuses.language, 'und') AS language, count(*) AS value FROM statuses INNER JOIN statuses_tags ON statuses_tags.status_id = statuses.id WHERE statuses_tags.tag_id = NULL AND statuses.id BETWEEN 111350145810432000 AND 111361470431232000 GROUP BY COALESCE(statuses.language, 'und') ORDER BY count(*) DESC LIMIT 10"
      }
    ]
  }
]