[
  {
    "caller": "activesupport",
    "callee": "Database"
  },
  {
    "caller": "activesupport",
    "callee": "app"
  },
  {
    "caller": "activesupport",
    "callee": "lib/paperclip"
  },
  {
    "caller": "activesupport",
    "callee": "logger"
  },
  {
    "caller": "app",
    "callee": "Database"
  },
  {
    "caller": "app",
    "callee": "activesupport"
  },
  {
    "caller": "app",
    "callee": "json"
  },
  {
    "caller": "app",
    "callee": "ruby"
  },
  {
    "caller": "app",
    "callee": "sidekiq"
  },
  {
    "caller": "sidekiq",
    "callee": "json"
  },
  {
    "caller": "sidekiq",
    "callee": "ruby"
  }
]